csv_json_converter_bruno_areis/__init__.py
csv_json_converter_bruno_areis/converter.py
csv_json_converter_bruno_areis-0.1.9.dist-info/entry_points.txt
csv_json_converter_bruno_areis-0.1.9.dist-info/WHEEL
csv_json_converter_bruno_areis-0.1.9.dist-info/METADATA
csv_json_converter_bruno_areis-0.1.9.dist-info/RECORD
